{"ID":23,"nodes":[{"outgoingEdges":[{"targetNode":11,"InterruptThreshold":1.0,"RequiredStates":["skip"],"Float_restrictions":[],"LastTriggeredTime":12456.9863,"Float_mult":[1.0,1.0,1.0,1.0,1.0,1.0],"Comparison_operators":[4,4,4,4,4,4]},{"targetNode":7,"InterruptThreshold":1.0,"RequiredStates":["skip"],"Float_restrictions":[],"LastTriggeredTime":12467.48,"Float_mult":[1.0,1.0,1.0,1.0,1.0,1.0],"Comparison_operators":[]},{"targetNode":2,"InterruptThreshold":0.0,"RequiredStates":[""],"Float_restrictions":[],"LastTriggeredTime":12473.9834,"Float_mult":[1.0,1.0,1.0,1.0,1.0,1.0,1.0],"Comparison_operators":[]},{"targetNode":3,"InterruptThreshold":0.693626344,"RequiredStates":[""],"Float_restrictions":[],"LastTriggeredTime":12454.9814,"Float_mult":[1.0,1.0,1.0,1.0,1.0,1.0,1.0],"Comparison_operators":[]},{"targetNode":12,"InterruptThreshold":1.0,"RequiredStates":["skip"],"Float_restrictions":[],"LastTriggeredTime":12470.9922,"Float_mult":[1.0,1.0,1.0,1.0,1.0,1.0],"Comparison_operators":[4,4,4,4,4,4]},{"targetNode":10,"InterruptThreshold":1.0,"RequiredStates":["skip"],"Float_restrictions":[],"LastTriggeredTime":12450.9873,"Float_mult":[1.0,1.0,1.0,1.0,1.0,1.0],"Comparison_operators":[4,4,4,4,4,4]},{"targetNode":1,"InterruptThreshold":0.0,"RequiredStates":[""],"Float_restrictions":[],"LastTriggeredTime":12464.9951,"Float_mult":[1.0,1.0,1.0,1.0,1.0,1.0,1.0],"Comparison_operators":[]},{"targetNode":0,"InterruptThreshold":0.01,"RequiredStates":[""],"Float_restrictions":[],"LastTriggeredTime":12442.9824,"Float_mult":[1.0,1.0,1.0,1.0,1.0,1.0,1.0],"Comparison_operators":[]}],"Actions":["Explore","Turn180"],"Reward":207.5722},{"outgoingEdges":[{"targetNode":8,"InterruptThreshold":1.0,"RequiredStates":["skip"],"Float_restrictions":[],"LastTriggeredTime":12459.4883,"Float_mult":[1.0,1.0,1.0,1.0,1.0,1.0],"Comparison_operators":[4,4,4,4,4,4]},{"targetNode":0,"InterruptThreshold":0.0,"RequiredStates":["skip"],"Float_restrictions":[],"LastTriggeredTime":12450.49,"Float_mult":[1.0,1.0,1.0,1.0,1.0,1.0,1.0],"Comparison_operators":[]},{"targetNode":4,"InterruptThreshold":1.0,"RequiredStates":["skip"],"Float_restrictions":[],"LastTriggeredTime":12476.9824,"Float_mult":[1.0,1.0,1.0,1.0,1.0,1.0],"Comparison_operators":[]},{"targetNode":11,"InterruptThreshold":1.0,"RequiredStates":["skip"],"Float_restrictions":[],"LastTriggeredTime":11034.4932,"Float_mult":[1.0,1.0,1.0,1.0,1.0,1.0],"Comparison_operators":[4,4,4,4,4,4]},{"targetNode":12,"InterruptThreshold":1.0,"RequiredStates":["skip"],"Float_restrictions":[],"LastTriggeredTime":12465.4922,"Float_mult":[1.0,1.0,1.0,1.0,1.0,1.0],"Comparison_operators":[4,4,4,4,4,4]},{"targetNode":0,"InterruptThreshold":0.99,"RequiredStates":[""],"Float_restrictions":[],"LastTriggeredTime":12462.9912,"Float_mult":[1.0,1.0,1.0,1.0,1.0,1.0,1.0],"Comparison_operators":[]},{"targetNode":3,"InterruptThreshold":0.571066439,"RequiredStates":[""],"Float_restrictions":[],"LastTriggeredTime":12407.49,"Float_mult":[1.0,1.0,1.0,1.0,1.0,1.0,1.0],"Comparison_operators":[]},{"targetNode":7,"InterruptThreshold":1.0,"RequiredStates":["skip"],"Float_restrictions":[],"LastTriggeredTime":12418.9893,"Float_mult":[1.0,1.0,1.0,1.0,1.0,1.0],"Comparison_operators":[]}],"Actions":["MoveTo","Shoot"],"Reward":55.3264732},{"outgoingEdges":[{"targetNode":13,"InterruptThreshold":1.0,"RequiredStates":["skip"],"Float_restrictions":[],"LastTriggeredTime":12463.9844,"Float_mult":[1.0,1.0,1.0,1.0,1.0,1.0],"Comparison_operators":[4,4,4,4,4,4]},{"targetNode":5,"InterruptThreshold":1.0,"RequiredStates":["skip"],"Float_restrictions":[],"LastTriggeredTime":12478.49,"Float_mult":[1.0,1.0,1.0,1.0,1.0,1.0],"Comparison_operators":[]},{"targetNode":0,"InterruptThreshold":0.07855082,"RequiredStates":[""],"Float_restrictions":[],"LastTriggeredTime":12468.9873,"Float_mult":[1.0,1.0,1.0,1.0,1.0,1.0,1.0],"Comparison_operators":[]},{"targetNode":2,"InterruptThreshold":0.0,"RequiredStates":[""],"Float_restrictions":[],"LastTriggeredTime":12474.48,"Float_mult":[1.0,1.0,1.0,1.0,1.0,1.0,1.0],"Comparison_operators":[]},{"targetNode":9,"InterruptThreshold":1.0,"RequiredStates":["skip"],"Float_restrictions":[],"LastTriggeredTime":12390.4824,"Float_mult":[1.0,1.0,1.0,1.0,1.0,1.0],"Comparison_operators":[4,4,4,4,4,4]},{"targetNode":0,"InterruptThreshold":0.99,"RequiredStates":[""],"Float_restrictions":[],"LastTriggeredTime":12456.49,"Float_mult":[1.0,1.0,1.0,1.0,1.0,1.0,1.0],"Comparison_operators":[]},{"targetNode":6,"InterruptThreshold":1.0,"RequiredStates":["skip"],"Float_restrictions":[],"LastTriggeredTime":12383.4912,"Float_mult":[1.0,1.0,1.0,1.0,1.0,1.0],"Comparison_operators":[]},{"targetNode":3,"InterruptThreshold":0.2726572,"RequiredStates":[""],"Float_restrictions":[],"LastTriggeredTime":12474.9941,"Float_mult":[1.0,1.0,1.0,1.0,1.0,1.0,1.0],"Comparison_operators":[]}],"Actions":["Shoot","Flee"],"Reward":48.931},{"outgoingEdges":[{"targetNode":14,"InterruptThreshold":1.0,"RequiredStates":["skip"],"Float_restrictions":[],"LastTriggeredTime":12472.4932,"Float_mult":[1.0,1.0,1.0,1.0,1.0,1.0],"Comparison_operators":[4,4,4,4,4,4]},{"targetNode":1,"InterruptThreshold":0.587867558,"RequiredStates":[""],"Float_restrictions":[],"LastTriggeredTime":12416.4873,"Float_mult":[1.0,1.0,1.0,1.0,1.0,1.0,1.0],"Comparison_operators":[]},{"targetNode":0,"InterruptThreshold":0.99,"RequiredStates":[""],"Float_restrictions":[],"LastTriggeredTime":12466.9824,"Float_mult":[1.0,1.0,1.0,1.0,1.0,1.0,1.0],"Comparison_operators":[]},{"targetNode":9,"InterruptThreshold":1.0,"RequiredStates":["skip"],"Float_restrictions":[],"LastTriggeredTime":12426.9814,"Float_mult":[1.0,1.0,1.0,1.0,1.0,1.0],"Comparison_operators":[4,4,4,4,4,4]},{"targetNode":4,"InterruptThreshold":1.0,"RequiredStates":["skip"],"Float_restrictions":[],"LastTriggeredTime":12475.4912,"Float_mult":[1.0,1.0,1.0,1.0,1.0,1.0],"Comparison_operators":[]},{"targetNode":10,"InterruptThreshold":1.0,"RequiredStates":["skip"],"Float_restrictions":[],"LastTriggeredTime":12397.9912,"Float_mult":[1.0,1.0,1.0,1.0,1.0,1.0],"Comparison_operators":[4,4,4,4,4,4]},{"targetNode":12,"InterruptThreshold":1.0,"RequiredStates":["skip"],"Float_restrictions":[],"LastTriggeredTime":12407.9873,"Float_mult":[1.0,1.0,1.0,1.0,1.0,1.0],"Comparison_operators":[4,4,4,4,4,4]},{"targetNode":11,"InterruptThreshold":1.0,"RequiredStates":["skip"],"Float_restrictions":[],"LastTriggeredTime":12389.4893,"Float_mult":[1.0,1.0,1.0,1.0,1.0,1.0],"Comparison_operators":[4,4,4,4,4,4]}],"Actions":["Reload","Explore"],"Reward":117.511963},{"outgoingEdges":[{"targetNode":3,"InterruptThreshold":0.2726572,"RequiredStates":[""],"Float_restrictions":[],"LastTriggeredTime":12480.9912,"Float_mult":[1.0,1.0,1.0,1.0,1.0,1.0,1.0],"Comparison_operators":[]},{"targetNode":0,"InterruptThreshold":0.07855082,"RequiredStates":[""],"Float_restrictions":[],"LastTriggeredTime":10977.4824,"Float_mult":[1.0,1.0,1.0,1.0,1.0,1.0,1.0],"Comparison_operators":[]},{"targetNode":0,"InterruptThreshold":1.0,"RequiredStates":["skip"],"Float_restrictions":[],"LastTriggeredTime":12401.99,"Float_mult":[1.0,1.0,1.0,1.0,1.0,1.0],"Comparison_operators":[]},{"targetNode":9,"InterruptThreshold":1.0,"RequiredStates":["skip"],"Float_restrictions":[],"LastTriggeredTime":12479.4844,"Float_mult":[1.0,1.0,1.0,1.0,1.0,1.0],"Comparison_operators":[4,4,4,4,4,4]},{"targetNode":2,"InterruptThreshold":0.0,"RequiredStates":[""],"Float_restrictions":[],"LastTriggeredTime":12455.9932,"Float_mult":[1.0,1.0,1.0,1.0,1.0,1.0,1.0],"Comparison_operators":[]},{"targetNode":8,"InterruptThreshold":1.0,"RequiredStates":["skip"],"Float_restrictions":[],"LastTriggeredTime":12396.98,"Float_mult":[1.0,1.0,1.0,1.0,1.0,1.0],"Comparison_operators":[4,4,4,4,4,4]},{"targetNode":5,"InterruptThreshold":1.0,"RequiredStates":["skip"],"Float_restrictions":[],"LastTriggeredTime":12475.9883,"Float_mult":[1.0,1.0,1.0,1.0,1.0,1.0],"Comparison_operators":[]},{"targetNode":0,"InterruptThreshold":0.99,"RequiredStates":[""],"Float_restrictions":[],"LastTriggeredTime":10958.4922,"Float_mult":[1.0,1.0,1.0,1.0,1.0,1.0,1.0],"Comparison_operators":[]},{"targetNode":3,"InterruptThreshold":1.0,"RequiredStates":["skip"],"Float_restrictions":[],"LastTriggeredTime":12412.9922,"Float_mult":[1.0,1.0,1.0,1.0,1.0,1.0],"Comparison_operators":[]}],"Actions":["Shoot","GoToCover"],"Reward":45.8794861},{"outgoingEdges":[{"targetNode":14,"InterruptThreshold":1.0,"RequiredStates":["skip"],"Float_restrictions":[],"LastTriggeredTime":12461.99,"Float_mult":[1.0,1.0,1.0,1.0,1.0,1.0],"Comparison_operators":[4,4,4,4,4,4]},{"targetNode":3,"InterruptThreshold":1.0,"RequiredStates":["skip"],"Float_restrictions":[],"LastTriggeredTime":12426.4844,"Float_mult":[1.0,1.0,1.0,1.0,1.0,1.0],"Comparison_operators":[]},{"targetNode":4,"InterruptThreshold":1.0,"RequiredStates":["skip"],"Float_restrictions":[],"LastTriggeredTime":12480.4941,"Float_mult":[1.0,1.0,1.0,1.0,1.0,1.0],"Comparison_operators":[]},{"targetNode":1,"InterruptThreshold":0.587867558,"RequiredStates":[""],"Float_restrictions":[],"LastTriggeredTime":12476.4854,"Float_mult":[1.0,1.0,1.0,1.0,1.0,1.0,1.0],"Comparison_operators":[]},{"targetNode":10,"InterruptThreshold":1.0,"RequiredStates":["skip"],"Float_restrictions":[],"LastTriggeredTime":12429.9854,"Float_mult":[1.0,1.0,1.0,1.0,1.0,1.0],"Comparison_operators":[4,4,4,4,4,4]},{"targetNode":8,"InterruptThreshold":1.0,"RequiredStates":["skip"],"Float_restrictions":[],"LastTriggeredTime":10967.4912,"Float_mult":[1.0,1.0,1.0,1.0,1.0,1.0],"Comparison_operators":[4,4,4,4,4,4]},{"targetNode":0,"InterruptThreshold":0.99,"RequiredStates":[""],"Float_restrictions":[],"LastTriggeredTime":12470.4951,"Float_mult":[1.0,1.0,1.0,1.0,1.0,1.0,1.0],"Comparison_operators":[]},{"targetNode":6,"InterruptThreshold":1.0,"RequiredStates":["skip"],"Float_restrictions":[],"LastTriggeredTime":12405.9824,"Float_mult":[1.0,1.0,1.0,1.0,1.0,1.0],"Comparison_operators":[]},{"targetNode":4,"InterruptThreshold":1.0,"RequiredStates":["skip"],"Float_restrictions":[],"LastTriggeredTime":12412.4951,"Float_mult":[1.0,1.0,1.0,1.0,1.0,1.0],"Comparison_operators":[]}],"Actions":["Reload","Explore","Shoot"],"Reward":50.2983932},{"outgoingEdges":[{"targetNode":0,"InterruptThreshold":0.07855082,"RequiredStates":[""],"Float_restrictions":[],"LastTriggeredTime":12403.4814,"Float_mult":[1.0,1.0,1.0,1.0,1.0,1.0,1.0],"Comparison_operators":[]},{"targetNode":0,"InterruptThreshold":0.99,"RequiredStates":[""],"Float_restrictions":[],"LastTriggeredTime":12395.4893,"Float_mult":[1.0,1.0,1.0,1.0,1.0,1.0,1.0],"Comparison_operators":[]},{"targetNode":3,"InterruptThreshold":0.2726572,"RequiredStates":[""],"Float_restrictions":[],"LastTriggeredTime":12466.4854,"Float_mult":[1.0,1.0,1.0,1.0,1.0,1.0,1.0],"Comparison_operators":[]},{"targetNode":8,"InterruptThreshold":1.0,"RequiredStates":["skip"],"Float_restrictions":[],"LastTriggeredTime":12383.9883,"Float_mult":[1.0,1.0,1.0,1.0,1.0,1.0],"Comparison_operators":[4,4,4,4,4,4]},{"targetNode":2,"InterruptThreshold":0.0,"RequiredStates":[""],"Float_restrictions":[],"LastTriggeredTime":12419.9834,"Float_mult":[1.0,1.0,1.0,1.0,1.0,1.0,1.0],"Comparison_operators":[]},{"targetNode":5,"InterruptThreshold":1.0,"RequiredStates":["skip"],"Float_restrictions":[],"LastTriggeredTime":12411.9814,"Float_mult":[1.0,1.0,1.0,1.0,1.0,1.0],"Comparison_operators":[]},{"targetNode":0,"InterruptThreshold":1.0,"RequiredStates":["skip"],"Float_restrictions":[],"LastTriggeredTime":12391.48,"Float_mult":[1.0,1.0,1.0,1.0,1.0,1.0],"Comparison_operators":[]},{"targetNode":2,"InterruptThreshold":1.0,"RequiredStates":["skip"],"Float_restrictions":[],"LastTriggeredTime":12468.49,"Float_mult":[1.0,1.0,1.0,1.0,1.0,1.0],"Comparison_operators":[]}],"Actions":["Shoot","Flee","MoveTo"],"Reward":42.4723167},{"outgoingEdges":[{"targetNode":11,"InterruptThreshold":1.0,"RequiredStates":["skip"],"Float_restrictions":[],"LastTriggeredTime":12417.4814,"Float_mult":[1.0,1.0,1.0,1.0,1.0,1.0],"Comparison_operators":[4,4,4,4,4,4]},{"targetNode":0,"InterruptThreshold":0.07855082,"RequiredStates":[""],"Float_restrictions":[],"LastTriggeredTime":11017.9951,"Float_mult":[1.0,1.0,1.0,1.0,1.0,1.0,1.0],"Comparison_operators":[]},{"targetNode":2,"InterruptThreshold":0.0,"RequiredStates":[""],"Float_restrictions":[],"LastTriggeredTime":10935.9873,"Float_mult":[1.0,1.0,1.0,1.0,1.0,1.0,1.0],"Comparison_operators":[]},{"targetNode":0,"InterruptThreshold":1.0,"RequiredStates":["skip"],"Float_restrictions":[],"LastTriggeredTime":12454.4922,"Float_mult":[1.0,1.0,1.0,1.0,1.0,1.0],"Comparison_operators":[]},{"targetNode":3,"InterruptThreshold":0.2726572,"RequiredStates":[""],"Float_restrictions":[],"LastTriggeredTime":10922.9932,"Float_mult":[1.0,1.0,1.0,1.0,1.0,1.0,1.0],"Comparison_operators":[]},{"targetNode":5,"InterruptThreshold":1.0,"RequiredStates":["skip"],"Float_restrictions":[],"LastTriggeredTime":10972.4941,"Float_mult":[1.0,1.0,1.0,1.0,1.0,1.0],"Comparison_operators":[]},{"targetNode":14,"InterruptThreshold":1.0,"RequiredStates":["skip"],"Float_restrictions":[],"LastTriggeredTime":12424.4961,"Float_mult":[1.0,1.0,1.0,1.0,1.0,1.0],"Comparison_operators":[4,4,4,4,4,4]},{"targetNode":5,"InterruptThreshold":1.0,"RequiredStates":["skip"],"Float_restrictions":[],"LastTriggeredTime":12405.4854,"Float_mult":[1.0,1.0,1.0,1.0,1.0,1.0],"Comparison_operators":[]},{"targetNode":6,"InterruptThreshold":1.0,"RequiredStates":["skip"],"Float_restrictions":[],"LastTriggeredTime":12467.9941,"Float_mult":[1.0,1.0,1.0,1.0,1.0,1.0],"Comparison_operators":[]},{"targetNode":13,"InterruptThreshold":1.0,"RequiredStates":["skip"],"Float_restrictions":[],"LastTriggeredTime":12453.4814,"Float_mult":[1.0,1.0,1.0,1.0,1.0,1.0],"Comparison_operators":[4,4,4,4,4,4]},{"targetNode":0,"InterruptThreshold":0.99,"RequiredStates":[""],"Float_restrictions":[],"LastTriggeredTime":12379.99,"Float_mult":[1.0,1.0,1.0,1.0,1.0,1.0,1.0],"Comparison_operators":[]}],"Actions":["Shoot","Flee","Explore"],"Reward":48.3311348},{"outgoingEdges":[{"targetNode":0,"InterruptThreshold":0.07855082,"RequiredStates":[""],"Float_restrictions":[],"LastTriggeredTime":12384.4854,"Float_mult":[1.0,1.0,1.0,1.0,1.0,1.0,1.0],"Comparison_operators":[]},{"targetNode":12,"InterruptThreshold":1.0,"RequiredStates":["skip"],"Float_restrictions":[],"LastTriggeredTime":11001.4834,"Float_mult":[1.0,1.0,1.0,1.0,1.0,1.0],"Comparison_operators":[4,4,4,4,4,4]},{"targetNode":0,"InterruptThreshold":0.99,"RequiredStates":[""],"Float_restrictions":[],"LastTriggeredTime":9812.494,"Float_mult":[1.0,1.0,1.0,1.0,1.0,1.0,1.0],"Comparison_operators":[]},{"targetNode":3,"InterruptThreshold":1.0,"RequiredStates":["skip"],"Float_restrictions":[],"LastTriggeredTime":6467.9917,"Float_mult":[1.0,1.0,1.0,1.0,1.0,1.0],"Comparison_operators":[4,4,4,4,4,4]},{"targetNode":3,"InterruptThreshold":0.2726572,"RequiredStates":[""],"Float_restrictions":[],"LastTriggeredTime":12459.9854,"Float_mult":[1.0,1.0,1.0,1.0,1.0,1.0,1.0],"Comparison_operators":[]},{"targetNode":5,"InterruptThreshold":1.0,"RequiredStates":["skip"],"Float_restrictions":[],"LastTriggeredTime":10992.4834,"Float_mult":[1.0,1.0,1.0,1.0,1.0,1.0],"Comparison_operators":[4,4,4,4,4,4]},{"targetNode":2,"InterruptThreshold":1.0,"RequiredStates":["skip"],"Float_restrictions":[],"LastTriggeredTime":9766.981,"Float_mult":[1.0,1.0,1.0,1.0,1.0,1.0],"Comparison_operators":[4,4,4,4,4,4]},{"targetNode":3,"InterruptThreshold":1.0,"RequiredStates":["skip"],"Float_restrictions":[],"LastTriggeredTime":12397.4941,"Float_mult":[1.0,1.0,1.0,1.0,1.0,1.0],"Comparison_operators":[]},{"targetNode":5,"InterruptThreshold":1.0,"RequiredStates":["skip"],"Float_restrictions":[],"LastTriggeredTime":12409.4951,"Float_mult":[1.0,1.0,1.0,1.0,1.0,1.0],"Comparison_operators":[]},{"targetNode":9,"InterruptThreshold":1.0,"RequiredStates":["skip"],"Float_restrictions":[],"LastTriggeredTime":10967.9873,"Float_mult":[1.0,1.0,1.0,1.0,1.0,1.0],"Comparison_operators":[4,4,4,4,4,4]},{"targetNode":2,"InterruptThreshold":0.0,"RequiredStates":[""],"Float_restrictions":[],"LastTriggeredTime":7950.9834,"Float_mult":[1.0,1.0,1.0,1.0,1.0,1.0,1.0],"Comparison_operators":[]},{"targetNode":4,"InterruptThreshold":1.0,"RequiredStates":["skip"],"Float_restrictions":[],"LastTriggeredTime":7990.488,"Float_mult":[1.0,1.0,1.0,1.0,1.0,1.0],"Comparison_operators":[4,4,4,4,4,4]},{"targetNode":0,"InterruptThreshold":1.0,"RequiredStates":["skip"],"Float_restrictions":[],"LastTriggeredTime":12445.4844,"Float_mult":[1.0,1.0,1.0,1.0,1.0,1.0],"Comparison_operators":[]}],"Actions":["GoToCover"],"Reward":40.6280251},{"outgoingEdges":[{"targetNode":6,"InterruptThreshold":1.0,"RequiredStates":["skip"],"Float_restrictions":[],"LastTriggeredTime":12390.9961,"Float_mult":[1.0,1.0,1.0,1.0,1.0,1.0],"Comparison_operators":[4,4,4,4,4,4]},{"targetNode":10,"InterruptThreshold":1.0,"RequiredStates":["skip"],"Float_restrictions":[],"LastTriggeredTime":11038.4883,"Float_mult":[1.0,1.0,1.0,1.0,1.0,1.0],"Comparison_operators":[4,4,4,4,4,4]},{"targetNode":13,"InterruptThreshold":1.0,"RequiredStates":["skip"],"Float_restrictions":[],"LastTriggeredTime":9769.483,"Float_mult":[1.0,1.0,1.0,1.0,1.0,1.0],"Comparison_operators":[4,4,4,4,4,4]},{"targetNode":5,"InterruptThreshold":1.0,"RequiredStates":["skip"],"Float_restrictions":[],"LastTriggeredTime":12479.98,"Float_mult":[1.0,1.0,1.0,1.0,1.0,1.0],"Comparison_operators":[]},{"targetNode":3,"InterruptThreshold":1.0,"RequiredStates":["skip"],"Float_restrictions":[],"LastTriggeredTime":12388.9912,"Float_mult":[1.0,1.0,1.0,1.0,1.0,1.0],"Comparison_operators":[]},{"targetNode":2,"InterruptThreshold":1.0,"RequiredStates":["skip"],"Float_restrictions":[],"LastTriggeredTime":6472.488,"Float_mult":[1.0,1.0,1.0,1.0,1.0,1.0],"Comparison_operators":[4,4,4,4,4,4]},{"targetNode":0,"InterruptThreshold":0.99,"RequiredStates":[""],"Float_restrictions":[],"LastTriggeredTime":12446.9922,"Float_mult":[1.0,1.0,1.0,1.0,1.0,1.0,1.0],"Comparison_operators":[]},{"targetNode":0,"InterruptThreshold":0.07855082,"RequiredStates":[""],"Float_restrictions":[],"LastTriggeredTime":12427.4941,"Float_mult":[1.0,1.0,1.0,1.0,1.0,1.0,1.0],"Comparison_operators":[]},{"targetNode":3,"InterruptThreshold":0.2726572,"RequiredStates":[""],"Float_restrictions":[],"LastTriggeredTime":12457.98,"Float_mult":[1.0,1.0,1.0,1.0,1.0,1.0,1.0],"Comparison_operators":[]},{"targetNode":0,"InterruptThreshold":1.0,"RequiredStates":["skip"],"Float_restrictions":[],"LastTriggeredTime":12376.4951,"Float_mult":[1.0,1.0,1.0,1.0,1.0,1.0],"Comparison_operators":[]},{"targetNode":0,"InterruptThreshold":1.0,"RequiredStates":["skip"],"Float_restrictions":[],"LastTriggeredTime":11022.9932,"Float_mult":[1.0,1.0,1.0,1.0,1.0,1.0],"Comparison_operators":[4,4,4,4,4,4]},{"targetNode":1,"InterruptThreshold":1.0,"RequiredStates":["skip"],"Float_restrictions":[],"LastTriggeredTime":9790.984,"Float_mult":[1.0,1.0,1.0,1.0,1.0,1.0],"Comparison_operators":[4,4,4,4,4,4]},{"targetNode":2,"InterruptThreshold":0.0,"RequiredStates":[""],"Float_restrictions":[],"LastTriggeredTime":12477.9932,"Float_mult":[1.0,1.0,1.0,1.0,1.0,1.0,1.0],"Comparison_operators":[]}],"Actions":["HealLarge","GoToCover","Explore"],"Reward":37.39203},{"outgoingEdges":[{"targetNode":8,"InterruptThreshold":1.0,"RequiredStates":["skip"],"Float_restrictions":[],"LastTriggeredTime":12373.4961,"Float_mult":[1.0,1.0,1.0,1.0,1.0,1.0],"Comparison_operators":[4,4,4,4,4,4]},{"targetNode":4,"InterruptThreshold":1.0,"RequiredStates":["skip"],"Float_restrictions":[],"LastTriggeredTime":12414.9795,"Float_mult":[1.0,1.0,1.0,1.0,1.0,1.0],"Comparison_operators":[4,4,4,4,4,4]},{"targetNode":9,"InterruptThreshold":1.0,"RequiredStates":["skip"],"Float_restrictions":[],"LastTriggeredTime":12380.99,"Float_mult":[1.0,1.0,1.0,1.0,1.0,1.0],"Comparison_operators":[4,4,4,4,4,4]},{"targetNode":3,"InterruptThreshold":0.571066439,"RequiredStates":[""],"Float_restrictions":[],"LastTriggeredTime":12398.4883,"Float_mult":[1.0,1.0,1.0,1.0,1.0,1.0,1.0],"Comparison_operators":[]},{"targetNode":7,"InterruptThreshold":1.0,"RequiredStates":["skip"],"Float_restrictions":[],"LastTriggeredTime":10941.9844,"Float_mult":[1.0,1.0,1.0,1.0,1.0,1.0],"Comparison_operators":[]},{"targetNode":4,"InterruptThreshold":1.0,"RequiredStates":["skip"],"Float_restrictions":[],"LastTriggeredTime":11023.9883,"Float_mult":[1.0,1.0,1.0,1.0,1.0,1.0],"Comparison_operators":[]},{"targetNode":0,"InterruptThreshold":0.0,"RequiredStates":["skip"],"Float_restrictions":[],"LastTriggeredTime":10947.4863,"Float_mult":[1.0,1.0,1.0,1.0,1.0,1.0,1.0],"Comparison_operators":[]},{"targetNode":0,"InterruptThreshold":1.0,"RequiredStates":["skip"],"Float_restrictions":[],"LastTriggeredTime":12430.4824,"Float_mult":[1.0,1.0,1.0,1.0,1.0,1.0],"Comparison_operators":[4,4,4,4,4,4]},{"targetNode":0,"InterruptThreshold":0.99,"RequiredStates":[""],"Float_restrictions":[],"LastTriggeredTime":12451.4844,"Float_mult":[1.0,1.0,1.0,1.0,1.0,1.0,1.0],"Comparison_operators":[]}],"Actions":["MoveTo","Shoot","Explore"],"Reward":46.52073},{"outgoingEdges":[{"targetNode":0,"InterruptThreshold":0.07855082,"RequiredStates":[""],"Float_restrictions":[],"LastTriggeredTime":12417.9951,"Float_mult":[1.0,1.0,1.0,1.0,1.0,1.0,1.0],"Comparison_operators":[]},{"targetNode":3,"InterruptThreshold":0.2726572,"RequiredStates":[""],"Float_restrictions":[],"LastTriggeredTime":12377.4883,"Float_mult":[1.0,1.0,1.0,1.0,1.0,1.0,1.0],"Comparison_operators":[]},{"targetNode":5,"InterruptThreshold":1.0,"RequiredStates":["skip"],"Float_restrictions":[],"LastTriggeredTime":12461.4932,"Float_mult":[1.0,1.0,1.0,1.0,1.0,1.0],"Comparison_operators":[4,4,4,4,4,4]},{"targetNode":4,"InterruptThreshold":1.0,"RequiredStates":["skip"],"Float_restrictions":[],"LastTriggeredTime":12396.4834,"Float_mult":[1.0,1.0,1.0,1.0,1.0,1.0],"Comparison_operators":[4,4,4,4,4,4]},{"targetNode":6,"InterruptThreshold":1.0,"RequiredStates":["skip"],"Float_restrictions":[],"LastTriggeredTime":12434.9922,"Float_mult":[1.0,1.0,1.0,1.0,1.0,1.0],"Comparison_operators":[]},{"targetNode":5,"InterruptThreshold":1.0,"RequiredStates":["skip"],"Float_restrictions":[],"LastTriggeredTime":11004.98,"Float_mult":[1.0,1.0,1.0,1.0,1.0,1.0],"Comparison_operators":[]},{"targetNode":1,"InterruptThreshold":1.0,"RequiredStates":["skip"],"Float_restrictions":[],"LastTriggeredTime":12364.99,"Float_mult":[1.0,1.0,1.0,1.0,1.0,1.0],"Comparison_operators":[4,4,4,4,4,4]},{"targetNode":2,"InterruptThreshold":0.0,"RequiredStates":[""],"Float_restrictions":[],"LastTriggeredTime":12431.4932,"Float_mult":[1.0,1.0,1.0,1.0,1.0,1.0,1.0],"Comparison_operators":[]},{"targetNode":0,"InterruptThreshold":0.99,"RequiredStates":[""],"Float_restrictions":[],"LastTriggeredTime":11012.4893,"Float_mult":[1.0,1.0,1.0,1.0,1.0,1.0,1.0],"Comparison_operators":[]},{"targetNode":9,"InterruptThreshold":1.0,"RequiredStates":["skip"],"Float_restrictions":[],"LastTriggeredTime":12457.4834,"Float_mult":[1.0,1.0,1.0,1.0,1.0,1.0],"Comparison_operators":[4,4,4,4,4,4]}],"Actions":["Shoot"],"Reward":42.801445},{"outgoingEdges":[{"targetNode":6,"InterruptThreshold":1.0,"RequiredStates":["skip"],"Float_restrictions":[],"LastTriggeredTime":12465.9893,"Float_mult":[1.0,1.0,1.0,1.0,1.0,1.0],"Comparison_operators":[]},{"targetNode":5,"InterruptThreshold":1.0,"RequiredStates":["skip"],"Float_restrictions":[],"LastTriggeredTime":12469.9814,"Float_mult":[1.0,1.0,1.0,1.0,1.0,1.0],"Comparison_operators":[4,4,4,4,4,4]},{"targetNode":13,"InterruptThreshold":1.0,"RequiredStates":["skip"],"Float_restrictions":[],"LastTriggeredTime":12408.4844,"Float_mult":[1.0,1.0,1.0,1.0,1.0,1.0],"Comparison_operators":[4,4,4,4,4,4]},{"targetNode":8,"InterruptThreshold":1.0,"RequiredStates":["skip"],"Float_restrictions":[],"LastTriggeredTime":11000.9873,"Float_mult":[1.0,1.0,1.0,1.0,1.0,1.0],"Comparison_operators":[4,4,4,4,4,4]},{"targetNode":0,"InterruptThreshold":0.99,"RequiredStates":[""],"Float_restrictions":[],"LastTriggeredTime":12443.9932,"Float_mult":[1.0,1.0,1.0,1.0,1.0,1.0,1.0],"Comparison_operators":[]},{"targetNode":0,"InterruptThreshold":0.07855082,"RequiredStates":[""],"Float_restrictions":[],"LastTriggeredTime":9248.488,"Float_mult":[1.0,1.0,1.0,1.0,1.0,1.0,1.0],"Comparison_operators":[]},{"targetNode":3,"InterruptThreshold":1.0,"RequiredStates":["skip"],"Float_restrictions":[],"LastTriggeredTime":10988.9893,"Float_mult":[1.0,1.0,1.0,1.0,1.0,1.0],"Comparison_operators":[4,4,4,4,4,4]},{"targetNode":1,"InterruptThreshold":1.0,"RequiredStates":["skip"],"Float_restrictions":[],"LastTriggeredTime":12441.9883,"Float_mult":[1.0,1.0,1.0,1.0,1.0,1.0],"Comparison_operators":[4,4,4,4,4,4]},{"targetNode":5,"InterruptThreshold":1.0,"RequiredStates":["skip"],"Float_restrictions":[],"LastTriggeredTime":12429.4883,"Float_mult":[1.0,1.0,1.0,1.0,1.0,1.0],"Comparison_operators":[]},{"targetNode":3,"InterruptThreshold":0.2726572,"RequiredStates":[""],"Float_restrictions":[],"LastTriggeredTime":12365.9844,"Float_mult":[1.0,1.0,1.0,1.0,1.0,1.0,1.0],"Comparison_operators":[]},{"targetNode":2,"InterruptThreshold":0.0,"RequiredStates":[""],"Float_restrictions":[],"LastTriggeredTime":12471.4893,"Float_mult":[1.0,1.0,1.0,1.0,1.0,1.0,1.0],"Comparison_operators":[]}],"Actions":["Shoot","Turn180","Reload"],"Reward":42.2663},{"outgoingEdges":[{"targetNode":0,"InterruptThreshold":0.99,"RequiredStates":[""],"Float_restrictions":[],"LastTriggeredTime":12464.4814,"Float_mult":[1.0,1.0,1.0,1.0,1.0,1.0,1.0],"Comparison_operators":[]},{"targetNode":4,"InterruptThreshold":1.0,"RequiredStates":["skip"],"Float_restrictions":[],"LastTriggeredTime":11015.4912,"Float_mult":[1.0,1.0,1.0,1.0,1.0,1.0],"Comparison_operators":[4,4,4,4,4,4]},{"targetNode":14,"InterruptThreshold":1.0,"RequiredStates":["skip"],"Float_restrictions":[],"LastTriggeredTime":9769.98,"Float_mult":[1.0,1.0,1.0,1.0,1.0,1.0],"Comparison_operators":[4,4,4,4,4,4]},{"targetNode":0,"InterruptThreshold":0.07855082,"RequiredStates":[""],"Float_restrictions":[],"LastTriggeredTime":12420.9932,"Float_mult":[1.0,1.0,1.0,1.0,1.0,1.0,1.0],"Comparison_operators":[]},{"targetNode":7,"InterruptThreshold":1.0,"RequiredStates":["skip"],"Float_restrictions":[],"LastTriggeredTime":12453.9951,"Float_mult":[1.0,1.0,1.0,1.0,1.0,1.0],"Comparison_operators":[4,4,4,4,4,4]},{"targetNode":2,"InterruptThreshold":0.0,"RequiredStates":[""],"Float_restrictions":[],"LastTriggeredTime":7972.4917,"Float_mult":[1.0,1.0,1.0,1.0,1.0,1.0,1.0],"Comparison_operators":[]},{"targetNode":8,"InterruptThreshold":1.0,"RequiredStates":["skip"],"Float_restrictions":[],"LastTriggeredTime":12408.9814,"Float_mult":[1.0,1.0,1.0,1.0,1.0,1.0],"Comparison_operators":[4,4,4,4,4,4]},{"targetNode":3,"InterruptThreshold":1.0,"RequiredStates":["skip"],"Float_restrictions":[],"LastTriggeredTime":12386.49,"Float_mult":[1.0,1.0,1.0,1.0,1.0,1.0],"Comparison_operators":[]},{"targetNode":3,"InterruptThreshold":0.2726572,"RequiredStates":[""],"Float_restrictions":[],"LastTriggeredTime":6456.492,"Float_mult":[1.0,1.0,1.0,1.0,1.0,1.0,1.0],"Comparison_operators":[]},{"targetNode":0,"InterruptThreshold":1.0,"RequiredStates":["skip"],"Float_restrictions":[],"LastTriggeredTime":12473.4863,"Float_mult":[1.0,1.0,1.0,1.0,1.0,1.0],"Comparison_operators":[]},{"targetNode":3,"InterruptThreshold":1.0,"RequiredStates":["skip"],"Float_restrictions":[],"LastTriggeredTime":6474.98926,"Float_mult":[1.0,1.0,1.0,1.0,1.0,1.0],"Comparison_operators":[4,4,4,4,4,4]},{"targetNode":5,"InterruptThreshold":1.0,"RequiredStates":["skip"],"Float_restrictions":[],"LastTriggeredTime":12436.4834,"Float_mult":[1.0,1.0,1.0,1.0,1.0,1.0],"Comparison_operators":[]}],"Actions":["HealLarge","GoToCover","Reload"],"Reward":21.8549633},{"outgoingEdges":[{"targetNode":11,"InterruptThreshold":1.0,"RequiredStates":["skip"],"Float_restrictions":[],"LastTriggeredTime":12460.9961,"Float_mult":[1.0,1.0,1.0,1.0,1.0,1.0],"Comparison_operators":[]},{"targetNode":6,"InterruptThreshold":1.0,"RequiredStates":["skip"],"Float_restrictions":[],"LastTriggeredTime":9726.482,"Float_mult":[1.0,1.0,1.0,1.0,1.0,1.0],"Comparison_operators":[]},{"targetNode":9,"InterruptThreshold":1.0,"RequiredStates":["skip"],"Float_restrictions":[],"LastTriggeredTime":12382.48,"Float_mult":[1.0,1.0,1.0,1.0,1.0,1.0],"Comparison_operators":[4,4,4,4,4,4]},{"targetNode":3,"InterruptThreshold":1.0,"RequiredStates":["skip"],"Float_restrictions":[],"LastTriggeredTime":9820.484,"Float_mult":[1.0,1.0,1.0,1.0,1.0,1.0],"Comparison_operators":[4,4,4,4,4,4]},{"targetNode":0,"InterruptThreshold":0.07855082,"RequiredStates":[""],"Float_restrictions":[],"LastTriggeredTime":12413.9863,"Float_mult":[1.0,1.0,1.0,1.0,1.0,1.0,1.0],"Comparison_operators":[]},{"targetNode":2,"InterruptThreshold":0.0,"RequiredStates":[""],"Float_restrictions":[],"LastTriggeredTime":12440.4922,"Float_mult":[1.0,1.0,1.0,1.0,1.0,1.0,1.0],"Comparison_operators":[]},{"targetNode":1,"InterruptThreshold":1.0,"RequiredStates":["skip"],"Float_restrictions":[],"LastTriggeredTime":12462.4932,"Float_mult":[1.0,1.0,1.0,1.0,1.0,1.0],"Comparison_operators":[4,4,4,4,4,4]},{"targetNode":0,"InterruptThreshold":0.99,"RequiredStates":[""],"Float_restrictions":[],"LastTriggeredTime":10987.4814,"Float_mult":[1.0,1.0,1.0,1.0,1.0,1.0,1.0],"Comparison_operators":[]},{"targetNode":13,"InterruptThreshold":1.0,"RequiredStates":["skip"],"Float_restrictions":[],"LastTriggeredTime":9759.987,"Float_mult":[1.0,1.0,1.0,1.0,1.0,1.0],"Comparison_operators":[]},{"targetNode":0,"InterruptThreshold":1.0,"RequiredStates":["skip"],"Float_restrictions":[],"LastTriggeredTime":0.0,"Float_mult":[1.0,1.0,1.0,1.0,1.0,1.0],"Comparison_operators":[]},{"targetNode":5,"InterruptThreshold":1.0,"RequiredStates":["skip"],"Float_restrictions":[],"LastTriggeredTime":12400.9893,"Float_mult":[1.0,1.0,1.0,1.0,1.0,1.0],"Comparison_operators":[]},{"targetNode":13,"InterruptThreshold":1.0,"RequiredStates":["skip"],"Float_restrictions":[],"LastTriggeredTime":12472.99,"Float_mult":[1.0,1.0,1.0,1.0,1.0,1.0],"Comparison_operators":[4,4,4,4,4,4]},{"targetNode":3,"InterruptThreshold":0.2726572,"RequiredStates":[""],"Float_restrictions":[],"LastTriggeredTime":12424.9932,"Float_mult":[1.0,1.0,1.0,1.0,1.0,1.0,1.0],"Comparison_operators":[]},{"targetNode":5,"InterruptThreshold":1.0,"RequiredStates":["skip"],"Float_restrictions":[],"LastTriggeredTime":12425.9873,"Float_mult":[1.0,1.0,1.0,1.0,1.0,1.0],"Comparison_operators":[]}],"Actions":["Shoot","Flee","Explore","Reload"],"Reward":33.7661819}],"BusyWithAction":0,"MutationIncrement":0.1,"TotalReward":127.421616,"ActionConstraints":{},"StateConstraints":{}}